test/D_FF_2.v
module d_ff(
    input wire clk,
    input wire D,
    input wire Rst,
    output reg Q
);

always @(negedge Rst or posedge clk)
begin
    if(!Rst)
        Q = 0;
    else
        Q= D;
end
endmodule

`timescale 1ns/1ps
module stimulus;
    reg clk;
    reg D;
    wire Q;
    reg Rst;
    d_ff d1(
        .clk(clk),
        .D(D),
        .Q(Q),
        .Rst(Rst)
    );
    integer i;
    initial begin
        $dumpfile("D_FF_2.vcd");
        $dumpvars(0,stimulus);
        D = 0;
        #8 D = 1;
        #10 D = 0;
        #10 D = 0;
        #10 D = 1;
        #10 D = 0;
        #10 D = 1;	
        #40;
    end
    initial begin
        clk = 0;
        for (i = 0; i<=10; i=i+1) begin
            #10 clk = ~clk;
        end
    end
    initial begin
        Rst = 1;
        #28 Rst = 0;
        #52 Rst = 1;
    end

endmodule

test/D_FF_2.vcd
$date
	Tue Sep 20 16:33:04 2022
$end
$version
	Icarus Verilog
$end
$timescale
	1ps
$end
$scope module stimulus $end
$var wire 1 ! Q $end
$var reg 1 " D $end
$var reg 1 # Rst $end
$var reg 1 $ clk $end
$var integer 32 % i [31:0] $end
$scope module d1 $end
$var wire 1 " D $end
$var wire 1 # Rst $end
$var wire 1 $ clk $end
$var reg 1 ! Q $end
$upscope $end
$upscope $end
$enddefinitions $end
$comment Show the parameter values. $end
$dumpall
$end
#0
$dumpvars
b0 %
0$
1#
0"
x!
$end
#8000
1"
#10000
1!
b1 %
1$
#18000
0"
#20000
b10 %
0$
#28000
0!
0#
#30000
b11 %
1$
#38000
1"
#40000
b100 %
0$
#48000
0"
#50000
b101 %
1$
#58000
1"
#60000
b110 %
0$
#70000
b111 %
1$
#80000
b1000 %
0$
1#
#90000
1!
b1001 %
1$
#100000
b1010 %
0$
#110000
b1011 %
1$
