test/exchange.v
`timescale 1ns/1ps

module exchange;
    reg a, b;
    initial begin
        a = 0;
        b = 0;
        #10
        a = 1;
        b = 2;
    end
    always begin
        #10
        a <= b;
        b <= a;
        if ($time >= 100) $finish;
    end
    initial begin
        $dumpfile("ex.vcd");
        $dumpvars;
    end
endmodule

test/ex.vcd
$date
	Sat Oct 15 11:10:23 2022
$end
$version
	Icarus Verilog
$end
$timescale
	1ps
$end
$scope module exchange $end
$var reg 1 ! a $end
$var reg 1 " b $end
$upscope $end
$enddefinitions $end
$comment Show the parameter values. $end
$dumpall
$end
#0
$dumpvars
0"
0!
$end
#10000
1"
0!
#20000
0"
1!
#30000
1"
0!
#40000
0"
1!
#50000
1"
0!
#60000
0"
1!
#70000
1"
0!
#80000
0"
1!
#90000
1"
0!
#100000
0"
1!
