exp5/model.v
module pla(x1,x2,y,W1,W2);
input[2:0]  x1,x2;
output y;
output[7:0] W1,W2;
wire [2:0] x1, x2;
reg y;
reg[7:0] sum;
reg[7:0] W1,W2;
function [15:0]w1w2;
    input [7:0]v1,v2;
    integer k;
    reg[7:0] w1, w2;
    reg [1:0] rand;
    begin
        w1=v1;
        w2=v2;
        for(k=1;k<=60;k=k+1)
        begin
            rand = {$random} % 10;
            if(rand == 0)
                w2=w2+2;        // x0 = (0, 2) t1 = 1
            else if(rand == 1)
                w2=w2+1;        // x1 = (0, 1) t2 = 1
            else if(rand == 2)
                w1=w1-2;        // x2 = (2, 0) t3 = -1
            else if(rand == 3)
                begin
                    w1=w1-2;    // x3 = (2, 2) t4 = -1
                    w2=w2-2;
                end
            else if(rand == 4)
                    w2=w2-3;    // x4 = (0, 3) t5 = 1
            else if(rand == 5)
                    w1=w1-1;    //x5 = (1, 0) t6 = -1
            else if(rand == 6)
                begin
                    w1=w1-2;    //x6 = (2, 1) t7 = -1
                    w2=w2-1;
                end
            else if(rand == 7)
                begin
                    w1=w1-1;    //x7 = (1, 2) t8 = -1
                    w2=w2-2;
                end
            else if(rand == 8)
                begin
                    w1=w1+1;    //x8 = (1, 4) t9 = 1
                    w2=w2+4;
                end
            else if(rand == 9)
                begin
                    w1=w1+0;    //x9 = (0, 7) t10 = 1
                    w2=w2+7;
                end
        end
        $display("w1 is %d, w2 is %d", w1, w2);
        w1w2 = {w1, w2};
    end
endfunction

initial begin
    {W1,W2}=w1w2(1,1);
end

always @(x1 or x2) 
begin
    sum = W1*x1+W2*x2;
    if((sum)>8'b01111111)
        y=0;
    else
        y=1;
    if (sum > 0)
        $display("(%d, %d), sum is %d, y is %d", x1, x2, $signed(sum), y);
end
endmodule


//~ `New testbench
`timescale  1ns / 1ps

module tb_pla;

// pla Parameters
parameter PERIOD  = 10;


// pla Inputs
reg  [2:0]  x1                            = 0 ;
reg  [2:0]  x2                            = 0 ;

// pla Outputs
wire  y                                    ;
wire  [7:0]  W1                            ;
wire  [7:0]  W2                            ;



pla  u_pla (
    .x1                      ( x1  [2:0] ),
    .x2                      ( x2  [2:0] ),

    .y                       ( y         ),
    .W1                      ( W1  [7:0] ),
    .W2                      ( W2  [7:0] )
);

initial begin
    $dumpfile("model.vcd");
    $dumpvars;
end

initial begin
    x1 <= 3'b000;
    x2 <= 3'b010;
    #PERIOD
    x1 <= 3'b000;
    x2 <= 3'b001;
    #PERIOD
    x1 <= 3'b010;
    x2 <= 3'b000;
    #PERIOD
    x1 <= 3'b010;
    x2 <= 3'b010;
    #PERIOD
    x1 <= 3'b001;
    x2 <= 3'b001;
    #PERIOD
    x1 <= 3'b001;
    x2 <= 3'b111;
    #PERIOD
    x1 <= 3'b010;
    x2 <= 3'b011;
    #PERIOD
    x1 <= 3'b000;
    x2 <= 3'b111;
    #PERIOD
    x1 <= 3'b001;
    x2 <= 3'b010;
    #PERIOD
    x1 <= 3'b001;
    x2 <= 3'b010;
    #PERIOD
    $finish;
end

endmodule

exp5/model.vcd
$date
	Mon Dec 26 12:46:30 2022
$end
$version
	Icarus Verilog
$end
$timescale
	1ps
$end
$scope module tb_pla $end
$var wire 1 ! y $end
$var wire 8 " W2 [7:0] $end
$var wire 8 # W1 [7:0] $end
$var reg 3 $ x1 [2:0] $end
$var reg 3 % x2 [2:0] $end
$scope module u_pla $end
$var wire 3 & x1 [2:0] $end
$var wire 3 ' x2 [2:0] $end
$var reg 8 ( W1 [7:0] $end
$var reg 8 ) W2 [7:0] $end
$var reg 8 * sum [7:0] $end
$var reg 1 ! y $end
$scope function w1w2 $end
$var reg 2 + rand [1:0] $end
$var reg 8 , v1 [7:0] $end
$var reg 8 - v2 [7:0] $end
$var reg 8 . w1 [7:0] $end
$var reg 16 / w1w2 [15:0] $end
$var reg 8 0 w2 [7:0] $end
$var integer 32 1 k [31:0] $end
$upscope $end
$upscope $end
$upscope $end
$enddefinitions $end
#0
$dumpvars
b111101 1
b10101 0
b1100101100010101 /
b11001011 .
b1 -
b1 ,
b10 +
b101010 *
b10101 )
b11001011 (
b10 '
b0 &
b10 %
b0 $
b11001011 #
b10101 "
1!
$end
#10000
b10101 *
b1 %
b1 '
#20000
0!
b10010110 *
b0 %
b0 '
b10 $
b10 &
#30000
b11000000 *
b10 %
b10 '
#40000
b11100000 *
b1 %
b1 '
b1 $
b1 &
#50000
1!
b1011110 *
b111 %
b111 '
#60000
0!
b11010101 *
b11 %
b11 '
b10 $
b10 &
#70000
b10010011 *
b111 %
b111 '
b0 $
b0 &
#80000
b11110101 *
b10 %
b10 '
b1 $
b1 &
