exp3/turing.v
module turing(clk,rst,seq,a,b,c);

input				clk, rst;
input 		[2:0]	a, b;
output reg	[3:0]	c;
output reg	[18:0]	seq;
wire		[7:0]	da, db;
reg		 	[2:0] 	state;
integer 			k;
parameter 	Q1_0 = 3'b00_0,
			Q1_1 = 3'b00_1,
			Q2_0 = 3'b01_0,
			Q2_1 = 3'b01_1,
			Q3_0 = 3'b10_0,
			Q3_1 = 3'b10_1,
			Q4_0 = 3'b11_0,
			Q4_1 = 3'b11_1;

fora 	U1(a,da);
forb	U2(b,db);

always @(posedge clk or negedge rst)
if(!rst)
	begin
		state	<= Q1_1;
		k		<= 8 - b;
		seq 	<= {1'b0,da,1'b0,db,1'b0};
	end
else
	begin
		case(state)
		Q1_1:	// 	q1	1	0	q1
			begin
				state	<= Q1_0;
				seq[k]	<= 0;
			end
		Q1_0:	//	q1	0	R	q2
			begin
				state 	<= Q2_1;
				k		<= k + 1;
			end
		Q2_1:	//	q2	1	R	q2
			begin
				if(seq[k])
						k <= k + 1;
				else
					state <= Q2_0;
			end
		Q2_0:	//	q2	0	1	q3
			begin
				state	<= Q3_1;
				seq[k]	<= 1;
			end
		Q3_1:	//	q3	1	R	q3
			begin
				if(seq[k])
					k <= k + 1;
				else
					state 	<= Q3_0;
			end
		Q3_0:	//	q3	0	L	q4
			begin
				k <= k - 1;
				state <= Q4_1;
			end
		Q4_1:	// q4	1	0	q4
			begin
				state	<= Q4_1;
				seq[k]	<= 0;
				// for(k=0;k<=18;k=k+1)
				// 	if(seq[k])
				// 		c<=c+1;
				// c<=c-1;
			end
		default:;
		endcase
	end
endmodule


module fora(a,band);
input 		[2:0]	a;
output reg	[7:0]	band;
always @(a)
	case(a)
		3'b000:band=1'b1;
		3'b001:band=2'b11;
		3'b010:band=3'b111;
		3'b011:band=4'b1111;
		3'b100:band=5'b1_1111;
		3'b101:band=6'b11_1111;
		3'b110:band=7'b111_1111;
		3'b111:band=8'b1111_1111;
	endcase
endmodule

module forb(b,band);
input 		[2:0]	b;
output reg	[7:0]	band;
always @(b)
	case(b)
		3'b000:band=8'b1000_0000;
		3'b001:band=8'b1100_0000;
		3'b010:band=8'b1110_0000;
		3'b011:band=8'b1111_0000;
		3'b100:band=8'b1111_1000;
		3'b101:band=8'b1111_1100;
		3'b110:band=8'b1111_1110;
		3'b111:band=8'b1111_1111;
	endcase
endmodule

//~ `New testbench
`timescale  1ns / 1ps

module tb_turing;

// turing Parameters
parameter PERIOD = 10     ;
parameter Q1_0  = 3'b00_0;

// turing Inputs
reg   clk                                  = 0 ;
reg   rst                                  = 0 ;
reg   [2:0]  a                             = 0 ;
reg   [2:0]  b                             = 0 ;

// turing Outputs
wire  [3:0]  c                             ;
wire  [18:0]  seq                          ;


initial
begin
    forever #(PERIOD/2)  clk=~clk;
end

initial
begin
    a <= 3'b101;
    b <= 3'b101;
    #(PERIOD*2) rst  =  1;
end

turing #(
    .Q1_0 ( Q1_0 ))
    u_turing (
    .clk                     ( clk         ),
    .rst                     ( rst         ),
    .a                       ( a    [2:0]  ),
    .b                       ( b    [2:0]  ),

    .c                       ( c    [3:0]  ),
    .seq                     ( seq  [18:0] )
);

initial
begin
    $dumpfile("turing.vcd");
    $dumpvars;
end

initial
begin
    #(PERIOD*20)
    $finish;
end

endmodule



/*module forc(seq,band);

input		[18:0]	seq;

output reg	[3:0]	band;

integer k;

always @(seq)

begin

	for(k=0;k<=18;k=k+1)

		if(seq[k])

			band=band+1;

	band=band-1;

end

endmodule*/

exp3/turing.vcd
$date
	Mon Nov 28 17:41:21 2022
$end
$version
	Icarus Verilog
$end
$timescale
	1ps
$end
$scope module tb_turing $end
$var wire 19 ! seq [18:0] $end
$var wire 4 " c [3:0] $end
$var reg 3 # a [2:0] $end
$var reg 3 $ b [2:0] $end
$var reg 1 % clk $end
$var reg 1 & rst $end
$scope module u_turing $end
$var wire 3 ' a [2:0] $end
$var wire 3 ( b [2:0] $end
$var wire 1 % clk $end
$var wire 1 & rst $end
$var wire 8 ) db [7:0] $end
$var wire 8 * da [7:0] $end
$var reg 4 + c [3:0] $end
$var reg 19 , seq [18:0] $end
$var reg 3 - state [2:0] $end
$var integer 32 . k [31:0] $end
$scope module U1 $end
$var wire 3 / a [2:0] $end
$var reg 8 0 band [7:0] $end
$upscope $end
$scope module U2 $end
$var wire 3 1 b [2:0] $end
$var reg 8 2 band [7:0] $end
$upscope $end
$upscope $end
$upscope $end
$enddefinitions $end
#0
$dumpvars
b11111100 2
b101 1
b111111 0
b101 /
b1000 .
b1 -
b0xxxxxxxx0xxxxxxxx0 ,
bx +
b111111 *
b11111100 )
b101 (
b101 '
0&
0%
b101 $
b101 #
bx "
b0xxxxxxxx0xxxxxxxx0 !
$end
#5000
b1111110111111000 !
b1111110111111000 ,
b11 .
1%
#10000
0%
#15000
1%
#20000
0%
1&
#25000
b1111110111110000 !
b1111110111110000 ,
b0 -
1%
#30000
0%
#35000
b100 .
b11 -
1%
#40000
0%
#45000
b101 .
1%
#50000
0%
#55000
b110 .
1%
#60000
0%
#65000
b111 .
1%
#70000
0%
#75000
b1000 .
1%
#80000
0%
#85000
b1001 .
1%
#90000
0%
#95000
b10 -
1%
#100000
0%
#105000
b1111111111110000 !
b1111111111110000 ,
b101 -
1%
#110000
0%
#115000
b1010 .
1%
#120000
0%
#125000
b1011 .
1%
#130000
0%
#135000
b1100 .
1%
#140000
0%
#145000
b1101 .
1%
#150000
0%
#155000
b1110 .
1%
#160000
0%
#165000
b1111 .
1%
#170000
0%
#175000
b10000 .
1%
#180000
0%
#185000
b100 -
1%
#190000
0%
#195000
b111 -
b1111 .
1%
